nktest/__init__.py
nktest/nktest.py
torch_nk/__init__.py
torch_nk/torch_nk.py
torch_nk-0.1.dist-info/METADATA
torch_nk-0.1.dist-info/WHEEL
torch_nk-0.1.dist-info/top_level.txt
torch_nk-0.1.dist-info/RECORD
