Metadata-Version: 2.1
Name: torch-nk
Version: 0.1
Summary: Implemetation XAI in Computer Vision (Pytorch)
Home-page: https://github.com/nobug-code/test_nk_2
Download-URL: https://github.com/nobug-code/test_nk_2/airplane.zip
Author: Namgil Kim
Author-email: tompx7564@gmail.com
License: UNKNOWN
Keywords: tootorch,XAI
Platform: UNKNOWN
Classifier: Programming Language :: Python :: 3
Classifier: Programming Language :: Python :: 3.6
Classifier: Programming Language :: Python :: 3.7
Classifier: Topic :: Scientific/Engineering :: Artificial Intelligence
Classifier: Topic :: Software Development :: Libraries :: Python Modules
Requires-Python: >=3.6
Requires-Dist: torch
Requires-Dist: torchvision
Requires-Dist: h5py
Requires-Dist: tqdm
Requires-Dist: opencv-python
Requires-Dist: requests
